[
  { "titles": "El Padrino", "characters": "Al Pacino", "anything": "Palomitas de maíz", "keyword": "MAFIA" },
  { "titles": "Titanic", "characters": "Leonardo DiCaprio", "anything": "Iceberg", "keyword": "NAUFRAGIO" },
  { "titles": "Volver al Futuro", "characters": "Michael J. Fox", "anything": "DeLorean", "keyword": "PARADOJA" },
  { "titles": "Jurassic Park", "characters": "Steven Spielberg", "anything": "Dinosaurio", "keyword": "EXTINCION" },
  { "titles": "El Señor de los Anillos", "characters": "Frodo", "anything": "Anillo de oro", "keyword": "MONTAÑA" },
  { "titles": "Matrix", "characters": "Keanu Reeves", "anything": "Pastilla roja", "keyword": "SIMULACION" },
  { "titles": "Forrest Gump", "characters": "Tom Hanks", "anything": "Caja de bombones", "keyword": "CORRER" },
  { "titles": "El Rey León", "characters": "Simba", "anything": "Sabana africana", "keyword": "MELENA" },
  { "titles": "Rápidos y Furiosos", "characters": "Vin Diesel", "anything": "Nitro", "keyword": "FAMILIA" },
  { "titles": "Piratas del Caribe", "characters": "Jack Sparrow", "anything": "Brújula", "keyword": "TESORO" },
  { "titles": "Avatar", "characters": "James Cameron", "anything": "Bosque fluorescente", "keyword": "AZUL" },
  { "titles": "Gladiador", "characters": "Russell Crowe", "anything": "Coliseo", "keyword": "VENGANZA" },
  { "titles": "El Joker", "characters": "Joaquin Phoenix", "anything": "Maquillaje", "keyword": "RISA" },
  { "titles": "Toy Story", "characters": "Woody", "anything": "Juguete de cuerda", "keyword": "AMISTAD" },
  { "titles": "Interestelar", "characters": "Matthew McConaughey", "anything": "Agujero negro", "keyword": "TIEMPO" },
  { "titles": "El Exorcista", "characters": "Linda Blair", "anything": "Crucifijo", "keyword": "POSESION" },
  { "titles": "Shrek", "characters": "Burro", "anything": "Pantano", "keyword": "OGRO" },
  { "titles": "Rocky", "characters": "Sylvester Stallone", "anything": "Guantes de box", "keyword": "CAMPEON" },
  { "titles": "Parásitos", "characters": "Bong Joon-ho", "anything": "Sótano", "keyword": "CLASE" },
  { "titles": "Nueve Reinas", "characters": "Ricardo Darín", "anything": "Estampilla", "keyword": "ESTAFA" },
  { "titles": "Harry Potter", "characters": "Emma Watson", "anything": "Varita mágica", "keyword": "HECHIZO" },
  { "titles": "Star Wars", "characters": "Darth Vader", "anything": "Sable de luz", "keyword": "LA FUERZA" },
  { "titles": "Los Vengadores", "characters": "Iron Man", "anything": "Escudo", "keyword": "HÉROES" },
  { "titles": "Batman", "characters": "Christian Bale", "anything": "Baticueva", "keyword": "MURCIÉLAGO" },
  { "titles": "Spider-Man", "characters": "Tom Holland", "anything": "Telaraña", "keyword": "ARAÑA" },
  { "titles": "Frozen", "characters": "Elsa", "anything": "Muñeco de nieve", "keyword": "HIELO" },
  { "titles": "Buscando a Nemo", "characters": "Dory", "anything": "Pecera", "keyword": "OCÉANO" },
  { "titles": "Rápido y Furioso", "characters": "Paul Walker", "anything": "Volante", "keyword": "CARRERA" },
  { "titles": "El Conjuro", "characters": "Annabelle", "anything": "Muñeca poseída", "keyword": "TERROR" },
  { "titles": "Volver al Futuro", "characters": "Doc Brown", "anything": "Reloj", "keyword": "VIAJE" },
  { "titles": "Coco", "characters": "Miguel", "anything": "Guitarra", "keyword": "MUERTOS" },
  { "titles": "Rápidos y Furiosos", "characters": "The Rock", "anything": "Cadena de oro", "keyword": "MÚSCULOS" },
  { "titles": "Piratas del Caribe", "characters": "Orlando Bloom", "anything": "Barco pirata", "keyword": "RON" },
  { "titles": "El Diario de Noa", "characters": "Ryan Gosling", "anything": "Carta de amor", "keyword": "ROMANCE" },
  { "titles": "It", "characters": "Pennywise", "anything": "Globo rojo", "keyword": "PAYASO" },
  { "titles": "Mi Villano Favorito", "characters": "Gru", "anything": "Minion", "keyword": "AMARILLO" },
  { "titles": "Rocky", "characters": "Apollo Creed", "anything": "Ring de box", "keyword": "GANCHO" },
  { "titles": "Terminator", "characters": "Arnold Schwarzenegger", "anything": "Robot", "keyword": "VOLVERÉ" },
  { "titles": "Cars", "characters": "Rayo McQueen", "anything": "Neumático", "keyword": "PISTA" },
  { "titles": "Rápido y Letal", "characters": "Jackie Chan", "anything": "Palillos chinos", "keyword": "KUNG FU" },
  { "titles": "Titanes del Pacífico", "characters": "El piloto", "anything": "Robot gigante", "keyword": "KAIJU" },
  { "titles": "Inception (El Origen)", "characters": "Leonardo DiCaprio", "anything": "Trompo", "keyword": "SUEÑO" },
  { "titles": "El Caballero de la Noche", "characters": "Heath Ledger", "anything": "Carta del Joker", "keyword": "CAOS" },
  { "titles": "Deadpool", "characters": "Ryan Reynolds", "anything": "Katanas", "keyword": "SARCASMO" },
  { "titles": "Guardianes de la Galaxia", "characters": "Groot", "anything": "Walkman", "keyword": "GALAXIA" },
  { "titles": "Thor", "characters": "Chris Hemsworth", "anything": "Martillo", "keyword": "TRUENO" },
  { "titles": "Black Panther", "characters": "T'Challa", "anything": "Garras", "keyword": "WAKANDA" },
  { "titles": "Doctor Strange", "characters": "Benedict Cumberbatch", "anything": "Capa roja", "keyword": "PORTAL" },
  { "titles": "Aquaman", "characters": "Jason Momoa", "anything": "Tridente", "keyword": "OCÉANO" },
  { "titles": "Wonder Woman", "characters": "Gal Gadot", "anything": "Lazo dorado", "keyword": "AMAZONA" },
  { "titles": "La La Land", "characters": "Emma Stone", "anything": "Piano", "keyword": "MUSICAL" },
  { "titles": "Bohemian Rhapsody", "characters": "Freddie Mercury", "anything": "Micrófono roto", "keyword": "QUEEN" },
  { "titles": "El Lobo de Wall Street", "characters": "Leonardo DiCaprio", "anything": "Fajos de billetes", "keyword": "AMBICIÓN" },
  { "titles": "Django sin Cadenas", "characters": "Jamie Foxx", "anything": "Revólver", "keyword": "VENGANZA" },
  { "titles": "Kill Bill", "characters": "Uma Thurman", "anything": "Traje amarillo", "keyword": "KATANA" },
  { "titles": "Scarface", "characters": "Tony Montana", "anything": "Puro", "keyword": "AMIGUITO" },
  { "titles": "El Silencio de los Inocentes", "characters": "Hannibal Lecter", "anything": "Máscara", "keyword": "CANÍBAL" },
  { "titles": "Psicosis", "characters": "Norman Bates", "anything": "Cortina de ducha", "keyword": "MOTEL" },
  { "titles": "Tiburón", "characters": "El pescador", "anything": "Aleta", "keyword": "MORDIDA" },
  { "titles": "Alien", "characters": "Ripley", "anything": "Nave espacial", "keyword": "XENOMORFO" },
  { "titles": "Depredador", "characters": "El cazador alienígena", "anything": "Visión térmica", "keyword": "SELVA" },
  { "titles": "Mad Max", "characters": "Furiosa", "anything": "Auto blindado", "keyword": "DESIERTO" },
  { "titles": "300", "characters": "Leónidas", "anything": "Escudo espartano", "keyword": "ESPARTA" },
  { "titles": "Intensa-Mente", "characters": "Alegría", "anything": "Esferas de recuerdos", "keyword": "EMOCIONES" },
  { "titles": "Up: Una Aventura de Altura", "characters": "Carl", "anything": "Globos", "keyword": "CASA" }
]
