[
  { "titles": "Breaking Bad", "characters": "Walter White", "anything": "Laboratorio", "keyword": "QUIMICA" },
  { "titles": "Game of Thrones", "characters": "Jon Snow", "anything": "Trono de hierro", "keyword": "DRAGON" },
  { "titles": "Stranger Things", "characters": "Once", "anything": "Bicicleta", "keyword": "PORTAL" },
  { "titles": "The Office", "characters": "Michael Scott", "anything": "Impresora", "keyword": "OFICINA" },
  { "titles": "Friends", "characters": "Ross Geller", "anything": "Sofá naranja", "keyword": "CAFETERIA" },
  { "titles": "La Casa de Papel", "characters": "El Profesor", "anything": "Máscara de Dalí", "keyword": "ATRACO" },
  { "titles": "The Last of Us", "characters": "Joel", "anything": "Hongo", "keyword": "INFECTADO" },
  { "titles": "Los Simpson", "characters": "Homero", "anything": "Rosquilla", "keyword": "SPRINGFIELD" },
  { "titles": "Peaky Blinders", "characters": "Thomas Shelby", "anything": "Gorra", "keyword": "BIRMINGHAM" },
  { "titles": "The Mandalorian", "characters": "Baby Yoda", "anything": "Casco beskar", "keyword": "GALAXIA" },
  { "titles": "Dark", "characters": "Jonas", "anything": "Cueva", "keyword": "TIEMPO" },
  { "titles": "Chernobyl", "characters": "Valery Legasov", "anything": "Reactor", "keyword": "RADIACION" },
  { "titles": "El Marginal", "characters": "Pastor", "anything": "Celda", "keyword": "PRISION" },
  { "titles": "Los Soprano", "characters": "Tony Soprano", "anything": "Pato", "keyword": "TERAPIA" },
  { "titles": "Rick y Morty", "characters": "Rick Sanchez", "anything": "Pistola de portales", "keyword": "MULTIVERSO" },
  { "titles": "Black Mirror", "characters": "Charlie Brooker", "anything": "Pantalla negra", "keyword": "DISTOPIA" },
  { "titles": "The Crown", "characters": "Reina Isabel", "anything": "Corona", "keyword": "MONARQUIA" },
  { "titles": "Sherlock", "characters": "Benedict Cumberbatch", "anything": "Lupa", "keyword": "DEDUCCION" },
  { "titles": "El Eternauta", "characters": "Juan Salvo", "anything": "Nevada mortal", "keyword": "INVASION" },
  { "titles": "Casados con Hijos", "characters": "Pepe Argento", "anything": "Sillón", "keyword": "FAMILIA" },
  { "titles": "Los Simpson", "characters": "Bart Simpson", "anything": "Pizarrón", "keyword": "DÓNUT" },
  { "titles": "Bob Esponja", "characters": "Patricio", "anything": "Hamburguesa", "keyword": "FONDO DE BIKINI" },
  { "titles": "Wednesday", "characters": "Merlina", "anything": "Trenzas", "keyword": "BAILE" },
  { "titles": "Squid Game", "characters": "El muñeco gigante", "anything": "Buzo verde", "keyword": "JUEGO" },
  { "titles": "The Big Bang Theory", "characters": "Sheldon Cooper", "anything": "Pizarra de física", "keyword": "BAZINGA" },
  { "titles": "Grey's Anatomy", "characters": "Meredith Grey", "anything": "Bisturí", "keyword": "HOSPITAL" },
  { "titles": "Prison Break", "characters": "Michael Scofield", "anything": "Tatuaje", "keyword": "FUGA" },
  { "titles": "The Walking Dead", "characters": "Rick Grimes", "anything": "Bate con alambre", "keyword": "ZOMBIE" },
  { "titles": "Modern Family", "characters": "Phil Dunphy", "anything": "Cámara casera", "keyword": "FAMILIA" },
  { "titles": "Vikingos", "characters": "Ragnar", "anything": "Hacha", "keyword": "VALHALLA" },
  { "titles": "Cómo Conocí a tu Madre", "characters": "Barney Stinson", "anything": "Traje", "keyword": "LEGEN-DARIO" },
  { "titles": "Merlí", "characters": "El profesor", "anything": "Pizarrón", "keyword": "FILOSOFÍA" },
  { "titles": "Élite", "characters": "El detective", "anything": "Uniforme del colegio", "keyword": "MISTERIO" },
  { "titles": "Los 100", "characters": "Clarke", "anything": "Nave espacial", "keyword": "APOCALIPSIS" },
  { "titles": "Chiquititas", "characters": "Cris Morena", "anything": "Orfanato", "keyword": "INFANCIA" },
  { "titles": "Rebelde Way", "characters": "Marizza", "anything": "Uniforme", "keyword": "ERREWAY" },
  { "titles": "Violetta", "characters": "Martina Stoessel", "anything": "Micrófono", "keyword": "DISNEY" },
  { "titles": "Patito Feo", "characters": "Las Divinas", "anything": "Diadema", "keyword": "POPULAR" },
  { "titles": "Floricienta", "characters": "Florencia Bertotti", "anything": "Vestido", "keyword": "CENICIENTA" },
  { "titles": "Los Simuladores", "characters": "El equipo", "anything": "Disfraz", "keyword": "PLAN" }
]
